{
  "/_not-found": "app/_not-found.js",
  "/admin/instructors/page": "app/admin/instructors/page.js",
  "/admin/courses/[id]/page": "app/admin/courses/[id]/page.js",
  "/admin/backup-restore/page": "app/admin/backup-restore/page.js",
  "/admin/courses/page": "app/admin/courses/page.js",
  "/admin/page": "app/admin/page.js",
  "/api/auth/[...nextauth]/route": "app/api/auth/[...nextauth]/route.js",
  "/api/admin/cleanup-orphaned/route": "app/api/admin/cleanup-orphaned/route.js",
  "/api/auth/approve-instructor/route": "app/api/auth/approve-instructor/route.js",
  "/api/auth/register/route": "app/api/auth/register/route.js",
  "/api/cohorts/route": "app/api/cohorts/route.js",
  "/api/competency-units/route": "app/api/competency-units/route.js",
  "/api/courses/[id]/analytics/route": "app/api/courses/[id]/analytics/route.js",
  "/api/courses/[id]/cohorts/route": "app/api/courses/[id]/cohorts/route.js",
  "/api/courses/[id]/enroll-cohort/route": "app/api/courses/[id]/enroll-cohort/route.js",
  "/api/courses/[id]/instructors/route": "app/api/courses/[id]/instructors/route.js",
  "/api/courses/[id]/lessons/route": "app/api/courses/[id]/lessons/route.js",
  "/api/courses/[id]/route": "app/api/courses/[id]/route.js",
  "/api/courses/route": "app/api/courses/route.js",
  "/api/courses/subscribe/route": "app/api/courses/subscribe/route.js",
  "/api/exercise-submissions/route": "app/api/exercise-submissions/route.js",
  "/api/exercises/[id]/students/route": "app/api/exercises/[id]/students/route.js",
  "/api/exercises/route": "app/api/exercises/route.js",
  "/api/exercises/[id]/route": "app/api/exercises/[id]/route.js",
  "/api/grades/route": "app/api/grades/route.js",
  "/api/init-db/route": "app/api/init-db/route.js",
  "/api/instructor/courses/[id]/lessons/route": "app/api/instructor/courses/[id]/lessons/route.js",
  "/api/instructor/courses/[id]/cohorts/[cohortId]/export/route": "app/api/instructor/courses/[id]/cohorts/[cohortId]/export/route.js",
  "/api/instructor/courses/[id]/cohorts/[cohortId]/route": "app/api/instructor/courses/[id]/cohorts/[cohortId]/route.js",
  "/api/instructor/courses/[id]/route": "app/api/instructor/courses/[id]/route.js",
  "/api/instructor/courses/[id]/students/[studentId]/route": "app/api/instructor/courses/[id]/students/[studentId]/route.js",
  "/api/lesson-notes/[id]/route": "app/api/lesson-notes/[id]/route.js",
  "/api/lessons/[id]/quiz/route": "app/api/lessons/[id]/quiz/route.js",
  "/api/lessons/[id]/route": "app/api/lessons/[id]/route.js",
  "/api/lesson-notes/route": "app/api/lesson-notes/route.js",
  "/api/lessons/[id]/exercises/route": "app/api/lessons/[id]/exercises/route.js",
  "/api/pdf-resources/[id]/route": "app/api/pdf-resources/[id]/route.js",
  "/api/lessons/route": "app/api/lessons/route.js",
  "/api/pdf-resources/route": "app/api/pdf-resources/route.js",
  "/api/quizzes/[id]/route": "app/api/quizzes/[id]/route.js",
  "/api/quiz-attempts/route": "app/api/quiz-attempts/route.js",
  "/api/quizzes/route": "app/api/quizzes/route.js",
  "/api/rubrics/criteria/[id]/route": "app/api/rubrics/criteria/[id]/route.js",
  "/api/rubrics/criteria/route": "app/api/rubrics/criteria/route.js",
  "/api/rubrics/[id]/route": "app/api/rubrics/[id]/route.js",
  "/api/student/courses/enroll/route": "app/api/student/courses/enroll/route.js",
  "/api/student/courses/unenroll/route": "app/api/student/courses/unenroll/route.js",
  "/api/student/exercises/[id]/route": "app/api/student/exercises/[id]/route.js",
  "/api/students/[id]/route": "app/api/students/[id]/route.js",
  "/api/students/route": "app/api/students/route.js",
  "/api/students/bulk/route": "app/api/students/bulk/route.js",
  "/api/unit-standards/[id]/route": "app/api/unit-standards/[id]/route.js",
  "/api/unit-standards/route": "app/api/unit-standards/route.js",
  "/auth/signin/page": "app/auth/signin/page.js",
  "/auth/register/page": "app/auth/register/page.js",
  "/courses/page": "app/courses/page.js",
  "/cohorts/page": "app/cohorts/page.js",
  "/instructor/courses/page": "app/instructor/courses/page.js",
  "/grade/[lessonId]/page": "app/grade/[lessonId]/page.js",
  "/grades/page": "app/grades/page.js",
  "/instructor/grades/page": "app/instructor/grades/page.js",
  "/instructor/courses/[id]/page": "app/instructor/courses/[id]/page.js",
  "/instructor/exercise/[exerciseId]/grade/page": "app/instructor/exercise/[exerciseId]/grade/page.js",
  "/instructor/lesson/[lessonId]/notes/page": "app/instructor/lesson/[lessonId]/notes/page.js",
  "/instructor/lesson/[lessonId]/page": "app/instructor/lesson/[lessonId]/page.js",
  "/instructor/page": "app/instructor/page.js",
  "/instructor/resources/page": "app/instructor/resources/page.js",
  "/instructor/rubric/[rubricId]/edit/page": "app/instructor/rubric/[rubricId]/edit/page.js",
  "/student/course/[courseId]/page": "app/student/course/[courseId]/page.js",
  "/page": "app/page.js",
  "/student/grades/page": "app/student/grades/page.js",
  "/instructor/students/page": "app/instructor/students/page.js",
  "/student/courses/page": "app/student/courses/page.js",
  "/student/quiz/[lessonId]/page": "app/student/quiz/[lessonId]/page.js",
  "/student/exercise/[exerciseId]/page": "app/student/exercise/[exerciseId]/page.js",
  "/student/page": "app/student/page.js",
  "/student/lesson/[lessonId]/page": "app/student/lesson/[lessonId]/page.js",
  "/students/page": "app/students/page.js",
  "/api/admin/stats/route": "app/api/admin/stats/route.js",
  "/api/cohorts/[id]/route": "app/api/cohorts/[id]/route.js",
  "/api/admin/restore/validate/route": "app/api/admin/restore/validate/route.js",
  "/api/admin/backup/route": "app/api/admin/backup/route.js",
  "/api/grades/analytics/route": "app/api/grades/analytics/route.js",
  "/api/grades/export/route": "app/api/grades/export/route.js",
  "/api/instructor/cohorts/[cohortId]/route": "app/api/instructor/cohorts/[cohortId]/route.js",
  "/api/instructor/cohorts/route": "app/api/instructor/cohorts/route.js",
  "/api/instructor/courses/route": "app/api/instructor/courses/route.js",
  "/api/instructor/cohorts/[cohortId]/export/route": "app/api/instructor/cohorts/[cohortId]/export/route.js",
  "/api/instructor/stats/route": "app/api/instructor/stats/route.js",
  "/api/instructors/route": "app/api/instructors/route.js",
  "/api/instructor/students/route": "app/api/instructor/students/route.js",
  "/api/lessons/unassigned/route": "app/api/lessons/unassigned/route.js",
  "/api/rubrics/criteria-levels/route": "app/api/rubrics/criteria-levels/route.js",
  "/api/rubrics/route": "app/api/rubrics/route.js",
  "/api/student/courses/route": "app/api/student/courses/route.js",
  "/api/admin/restore/route": "app/api/admin/restore/route.js",
  "/api/cohorts/[id]/export/route": "app/api/cohorts/[id]/export/route.js"
}